HISTORY.md
LICENSE
MANIFEST.in
README.md
flask_schema.py
setup.py
flask_schema.egg-info/PKG-INFO
flask_schema.egg-info/SOURCES.txt
flask_schema.egg-info/dependency_links.txt
flask_schema.egg-info/not-zip-safe
flask_schema.egg-info/requires.txt
flask_schema.egg-info/top_level.txt