Metadata-Version: 1.1
Name: flask-schema
Version: 0.1a
Summary: Schema Validation for your JSON APIs
Home-page: http://github.com/rhyselsmore/flask-schema
Author: Rhys Elsmore
Author-email: me@rhys.io
License: Copyright (c) 2015, Rhys Elsmore <me@rhys.io>
